dashlib/__init__.py
dashlib-0.1.dist-info/licenses/LICENSE
dashlib-0.1.dist-info/METADATA
dashlib-0.1.dist-info/WHEEL
dashlib-0.1.dist-info/top_level.txt
dashlib-0.1.dist-info/RECORD
